{"cameraMode":{"drawMode":0,"name":"Shaded","section":"Shading Mode"},"sceneLighting":true,"audioPlay":false,"sceneViewState":{"m_AlwaysRefresh":false,"showFog":true,"showSkybox":true,"showFlares":true,"showImageEffects":true,"showParticleSystems":true,"showVisualEffectGraphs":true,"m_FxEnabled":true},"in2DMode":false,"pivot":{"x":62.41950225830078,"y":-36.82117462158203,"z":62.53324890136719},"rotation":{"x":-0.18622809648513795,"y":-0.3920571506023407,"z":0.08129803091287613,"w":-0.8972835540771484},"size":53.2442626953125,"orthographic":false}